README.txt
setup.py
gittools/__init__.py
gittools/gittools.py
gittools/logging/__init__.py
gittools/logging/constants.py
gittools/logging/log_entry.py
gittools/logging/logger.py
gittools/program/__init__.py
gittools/program/program_class.py
gittools/program/shell_ops.py
gittools/program/directory_traversal/__init__.py
gittools/program/directory_traversal/delegates.py
gittools/program/directory_traversal/directory_runner.py
gittools/program/directory_traversal/directory_tree.py
gittools/program/json_traversal/__init__.py
gittools/program/json_traversal/json_runner.py
jtitor_gittools.egg-info/PKG-INFO
jtitor_gittools.egg-info/SOURCES.txt
jtitor_gittools.egg-info/dependency_links.txt
jtitor_gittools.egg-info/entry_points.txt
jtitor_gittools.egg-info/top_level.txt