Metadata-Version: 1.0
Name: jtitor-gittools
Version: 0.1.6
Summary: Batches common bulk operations on git repositories, but privately listed since it's not quite done.
Home-page: http://pypi.python.org/pypi/jtitor_gittools/0.1.6/
Author: jTitor
Author-email: name@addr.ess
License: MIT
Platform: UNKNOWN
